ThreeDVG/__init__.py
ThreeDVG/app.py
3DVG-0.1.0.dist-info/METADATA
3DVG-0.1.0.dist-info/WHEEL
3DVG-0.1.0.dist-info/top_level.txt
3DVG-0.1.0.dist-info/RECORD
