Metadata-Version: 2.1
Name: 3DVG
Version: 0.1.0
Summary: Visual Ground
Home-page: https://github.com/yjzhao19981027/3DVG
Download-URL: https://github.com/yjzhao19981027/3DVG/tags
Author: Yinjie Zhao
Author-email: 630877986@qq.com
Requires-Python: >=3.7
Requires-Dist: pillow
Requires-Dist: aiofiles
Requires-Dist: fastapi
Requires-Dist: uvicorn[standard]
Requires-Dist: python-multipart
Requires-Dist: ftfy
Requires-Dist: regex
Requires-Dist: tqdm
